textTableImproved/__init__.py
textTableImproved-0.0.1.dist-info/LICENSE
textTableImproved-0.0.1.dist-info/METADATA
textTableImproved-0.0.1.dist-info/WHEEL
textTableImproved-0.0.1.dist-info/top_level.txt
textTableImproved-0.0.1.dist-info/RECORD
