Metadata-Version: 2.1
Name: textTableImproved
Version: 0.0.1
Summary: text table drawer improved
Author: Maxim Taran
Author-email: tmasik.t.210@gmail.com
Classifier: Programming Language :: Python :: 3
Classifier: License :: OSI Approved :: MIT License
Classifier: Operating System :: OS Independent
Requires-Python: >=3.7
License-File: LICENSE
